[
    {
        "menuId":"nav1",
        "title": "동물을 찾습니다",
        "menus": [
            {"label": "실종동물 찾습니다", "to":"#"},
            {"label":"주인을 찾습니다", "to":"#"},
            {"label":"주인 찾았어요", "to":"#"}
        ]
    },
    {
        "menuId":"nav2",
        "title": "무료 분양",
        "menus": [
            {"label":"분양합니다", "to":"#"},
            {"label":"안전 분양 완료!", "to":"#"}
        ]
    },
    {
        "menuId":"nav3",
        "title": "봉사/후원하기",
        "menus": [
            {"label":"자원봉사 모집", "to":"#"},
            {"label":"기부&후원 요청", "to":"#"},
            {"label":"나눔합니다", "to":"#"}
        ]
    },
    {
        "menuId":"nav4",
        "title": "커뮤니티",
        "menus": [
            {"label":"공지사항", "to":"#"},
            {"label":"반려동물 이야기", "to":"#"}
        ]
    }
]